pycent-1.0.dist-info/WHEEL
pycent-1.0.dist-info/zip-safe
pycent-1.0.dist-info/RECORD
pycent-1.0.dist-info/DESCRIPTION.rst
pycent-1.0.dist-info/metadata.json
pycent-1.0.dist-info/METADATA
pycent-1.0.dist-info/top_level.txt
pycent/__init__.py
