Metadata-Version: 2.0
Name: pycent
Version: 1.0
Summary: Calculate the percentage of a value, or the reverse
Home-page: http://github.com/LordFlashmeow/pycent
Author: LordFlashmeow
Author-email: lordflashmeow@gmail.com
License: MIT
Keywords: percent percentage math
Platform: UNKNOWN
Classifier: Intended Audience :: Developers
Classifier: License :: OSI Approved :: MIT License
Classifier: Programming Language :: Python :: 2.7
Classifier: Programming Language :: Python :: 3.2
Classifier: Programming Language :: Python :: 3.3
Classifier: Programming Language :: Python :: 3.4
Classifier: Programming Language :: Python :: 3.5
Classifier: Programming Language :: Python :: 3.6
Classifier: Topic :: Scientific/Engineering :: Mathematics
